nmk_base/__init__.py
nmk_base/backends.py
nmk_base/buildenv.py
nmk_base/buildenv.yml
nmk_base/common.py
nmk_base/git.py
nmk_base/git.yml
nmk_base/helpers.py
nmk_base/helpers.yml
nmk_base/output.yml
nmk_base/plugin.yml
nmk_base/resolvers.py
nmk_base/sysdeps.py
nmk_base/sysdeps.yml
nmk_base/tasks.yml
nmk_base/venv.yml
nmk_base/venvbuilder.py
nmk_base/version.py
nmk_base/_buildenv/__init__.py
nmk_base/_buildenv/extension.py
nmk_base/_buildenv/legacy.py
nmk_base/templates/__init__.py
nmk_base/templates/gitattributes
nmk_base/templates/gitignore
nmk_base/templates/requirements.txt
nmk_base-1.2.0.dist-info/licenses/LICENSE
nmk_base-1.2.0.dist-info/METADATA
nmk_base-1.2.0.dist-info/WHEEL
nmk_base-1.2.0.dist-info/entry_points.txt
nmk_base-1.2.0.dist-info/top_level.txt
nmk_base-1.2.0.dist-info/RECORD
