Metadata-Version: 2.4
Name: nmk-base
Version: 1.2.0
Summary: Base plugin for nmk build system
Author: The dynod project
Maintainer: The dynod project
License: MIT License
Project-URL: Homepage, https://github.com/dynod/nmk-base
Project-URL: Repository, https://github.com/dynod/nmk-base
Project-URL: Issues, https://github.com/dynod/nmk/issues?q=is%3Aopen+is%3Aissue+label%3Aplugin%3Abase
Classifier: Programming Language :: Python :: 3.10
Classifier: Programming Language :: Python :: 3.11
Classifier: Programming Language :: Python :: 3.12
Classifier: Programming Language :: Python :: 3.13
Classifier: Programming Language :: Python :: 3.14
Requires-Python: >=3.10
License-File: LICENSE
Requires-Dist: Jinja2
Requires-Dist: nmk>=1.4.0
Requires-Dist: buildenv
Requires-Dist: tomlkit
Dynamic: license-file
